EzCommit/__init__.py
EzCommit/config.py
EzCommit/constants.py
EzCommit/main.py
EzCommit/controller/__init__.py
EzCommit/controller/controller.py
EzCommit/helper/__init__.py
EzCommit/helper/default_convention.py
EzCommit/helper/default_convention.txt
EzCommit/model/__init__.py
EzCommit/model/model.py
EzCommit/model/repository.py
EzCommit/model/utils.py
EzCommit/rag/__init__.py
EzCommit/rag/ingest.py
EzCommit/rag/rag.py
EzCommit/rag/utils.py
EzCommit/tests/__init__.py
EzCommit/tests/test_create_pr.py
EzCommit/tests/test_gen_cmt.py
EzCommit/tests/test_gen_cmt_fast.py
EzCommit/tests/test_import_file.py
EzCommit/tests/test_visual.py
EzCommit/view/__init__.py
EzCommit/view/view.py
ezcommit02-0.9.dist-info/METADATA
ezcommit02-0.9.dist-info/WHEEL
ezcommit02-0.9.dist-info/entry_points.txt
ezcommit02-0.9.dist-info/top_level.txt
ezcommit02-0.9.dist-info/RECORD
