Metadata-Version: 2.1
Name: ezcommit02
Version: 0.9
Requires-Dist: chromadb >=0.5.0
Requires-Dist: click >=8.1.7
Requires-Dist: openai >=1.33.0
Requires-Dist: GitPython >=3.1.43
Requires-Dist: markdown >=3.6
Requires-Dist: pdfkit
Requires-Dist: PyGithub
